pyfortyseven/__init__.py
pyfortyseven/secrets.py
pyfortyseven-0.0.1.dist-info/METADATA
pyfortyseven-0.0.1.dist-info/WHEEL
pyfortyseven-0.0.1.dist-info/top_level.txt
pyfortyseven-0.0.1.dist-info/RECORD
